LICENSE
MANIFEST.in
README
setup.cfg
setup.py
sphinxcontrib/__init__.py
sphinxcontrib/whooshindex.py
sphinxcontrib_whoosh.egg-info/PKG-INFO
sphinxcontrib_whoosh.egg-info/SOURCES.txt
sphinxcontrib_whoosh.egg-info/dependency_links.txt
sphinxcontrib_whoosh.egg-info/namespace_packages.txt
sphinxcontrib_whoosh.egg-info/requires.txt
sphinxcontrib_whoosh.egg-info/top_level.txt
sphinxcontrib_whoosh.egg-info/zip-safe