Metadata-Version: 1.0
Name: sphinxcontrib-whoosh
Version: 0.1
Summary: Whoosh Sphinx extension
Home-page: http://packages.python.org/sphinxcontrib-whoosh/
Author: Pauli Virtanen
Author-email: pav@iki.fi
License: BSD
Download-URL: http://pypi.python.org/pypi/sphinxcontrib-whoosh
Platform: any
Classifier: Development Status :: 3 - Alpha
Classifier: Environment :: Console
Classifier: Environment :: Web Environment
Classifier: Intended Audience :: Developers
Classifier: License :: Public Domain
Classifier: Operating System :: OS Independent
Classifier: Programming Language :: Python
Classifier: Topic :: Documentation
Classifier: Topic :: Utilities
